dinjections/__init__.py
dinjections/app.py
dinjections/exceptions.py
dinjections/lifecycle.py
dinjections/module.py
dinjections/options.py
dinjections-1.1.1.dist-info/LICENSE
dinjections-1.1.1.dist-info/METADATA
dinjections-1.1.1.dist-info/WHEEL
dinjections-1.1.1.dist-info/top_level.txt
dinjections-1.1.1.dist-info/RECORD
