Metadata-Version: 2.1
Name: dinjections
Version: 1.1.1
Summary: Dependency injection framework based on uber.fx for python
Author-email: Francisco Escher Guimarães da Silva <egs.francisco@gmail.com>
License: MIT License
Project-URL: repository, https://github.com/franciscoescher/dinjections
Keywords: di,dependency injeciton,fx,framework,dinjections
Classifier: License :: OSI Approved :: MIT License
Classifier: Programming Language :: Python
Classifier: Programming Language :: Python :: 3
Requires-Python: >=3.6
License-File: LICENSE
Provides-Extra: dev
